xfyunsdkocr/__init__.py
xfyunsdkocr/bank_card_client.py
xfyunsdkocr/business_card_client.py
xfyunsdkocr/finger_ocr_client.py
xfyunsdkocr/general_words_client.py
xfyunsdkocr/image_word_client.py
xfyunsdkocr/intsig_ocr_client.py
xfyunsdkocr/invoice_ocr_client.py
xfyunsdkocr/itr_ocr_client.py
xfyunsdkocr/jd_ocr_client.py
xfyunsdkocr/llm_ocr_client.py
xfyunsdkocr/pd_rec_client.py
xfyunsdkocr/rec_ocr_client.py
xfyunsdkocr-0.0.3.dist-info/LICENSE
xfyunsdkocr-0.0.3.dist-info/METADATA
xfyunsdkocr-0.0.3.dist-info/WHEEL
xfyunsdkocr-0.0.3.dist-info/top_level.txt
xfyunsdkocr-0.0.3.dist-info/RECORD
